{
  "project_info": {
    "project_number": "793044851352",
    "project_id": "nuscan-1660905612866",
    "storage_bucket": "nuscan-1660905612866.appspot.com"
  },
  "client": [
    {
      "client_info": {
        "mobilesdk_app_id": "1:793044851352:android:93e533d095aaac97d74eed",
        "android_client_info": {
          "package_name": "com.example.nuscan"
        }
      },
      "oauth_client": [
        {
          "client_id": "793044851352-1pkue299h0j1ntouoe30hfipkm1371ae.apps.googleusercontent.com",
          "client_type": 1,
          "android_info": {
            "package_name": "com.example.nuscan",
            "certificate_hash": "7ab5e182b0e86a71f7cb7db24697f080f3489661"
          }
        },
        {
          "client_id": "793044851352-sdmk4g63qg8j9bc3uj9128rlci1m23ja.apps.googleusercontent.com",
          "client_type": 3
        }
      ],
      "api_key": [
        {
          "current_key": "AIzaSyB2tepAd6UFFKj4fYvzeu83QVXnRGNs8uo"
        }
      ],
      "services": {
        "appinvite_service": {
          "other_platform_oauth_client": [
            {
              "client_id": "793044851352-sdmk4g63qg8j9bc3uj9128rlci1m23ja.apps.googleusercontent.com",
              "client_type": 3
            }
          ]
        }
      }
    }
  ],
  "configuration_version": "1"
}